{
  "crawl_metadata": {
    "start_url": "https://www.siza.io/",
    "base_domain": "www.siza.io",
    "results_file": null,
    "crawl_start_time": "2025-04-05T17:52:18.007779",
    "crawl_end_time": "2025-04-05T17:52:45.473750",
    "total_crawl_time_seconds": 27.46594476699829,
    "max_pages_limit": 3,
    "max_depth_limit": 1,
    "concurrency_limit": 5,
    "resource_blocking_enabled": true,
    "total_pages_processed": 1,
    "successful_pages_analyzed": 1,
    "failed_or_error_pages": 0
  },
  "crawl_summary": {
    "identified_product_names": [
      "Siza"
    ],
    "identified_company_names": [
      "Selano Health (PTY) Ltd",
      "Siza"
    ],
    "contact_emails": [
      "hello@siza.io"
    ],
    "contact_phones": [
      "+27 (68) 490 9328"
    ],
    "page_topics_summary": {
      "Product/Service Page": 1
    }
  },
  "pages": [
    {
      "url": "https://www.siza.io/",
      "depth": 0,
      "analysis": {
        "page_topic": "Product/Service Page",
        "product_name": "Siza",
        "company_name_mentioned": [
          "Siza",
          "Selano Health (PTY) Ltd"
        ],
        "description_summary": "Siza offers online doctor consultations with features like virtual vital tests, digital prescriptions, and emergency mode for immediate assistance. The service is SAHPRA registered and aims to provide convenient healthcare access.",
        "pricing": {
          "details": "$30 for General Practitioner consultations, $50 for emergency consultations, $120 for specialist consultations",
          "currency": "USD"
        },
        "duration": null,
        "target_audience": "Patients needing online doctor consultations",
        "prerequisites": null,
        "key_features_or_benefits": [
          "Virtual body vital tests using AI-based technology",
          "Emergency Mode for immediate doctor assistance",
          "Digital prescriptions accepted at pharmacies",
          "Video consultation with doctors",
          "Access to a variety of specialists"
        ],
        "learning_outcomes": [],
        "enrollment_info": "Download the Siza app to access video consultations with doctors.",
        "company_usp_mentioned": [
          "SAHPRA registered",
          "Verified doctors",
          "Trusted by patients",
          "Virtual vital testing",
          "24/7 availability"
        ],
        "contact_email": "hello@siza.io",
        "contact_phone": "+27 (68) 490 9328",
        "extracted_from_url": "https://www.siza.io/"
      },
      "links_found": [
        "https://www.siza.io/about_us",
        "https://www.siza.io/how-it-works",
        "https://www.siza.io",
        "https://www.siza.io/pricing"
      ],
      "crawl_time": 25.633084774017334,
      "status": "success"
    }
  ]
}